strlib/__init__.py
strlib/_decorators.py
strlib/_exceptions.py
strlib/_parser.py
strlib-0.0.0.dist-info/LICENSE
strlib-0.0.0.dist-info/METADATA
strlib-0.0.0.dist-info/WHEEL
strlib-0.0.0.dist-info/top_level.txt
strlib-0.0.0.dist-info/RECORD
