Metadata-Version: 2.1
Name: strlib
Version: 0.0.0
Summary: Collection of utility functions for modifying strings
Home-page: https://github.com/GH-Syn/strlib
Author: Joshua Rose and individual contributors
Author-email: joshuarose099@gmail.com
Project-URL: Source, https://github.com/GH-Syn/strlib
Project-URL: Documentation, https://gh-syn.github.io/strlib/
Classifier: Intended Audience :: Developers
Classifier: License :: OSI Approved :: Apache Software License
Classifier: Natural Language :: English
Classifier: Operating System :: MacOS :: MacOS X
Classifier: Operating System :: POSIX
Classifier: Operating System :: POSIX :: BSD
Classifier: Operating System :: POSIX :: Linux
Classifier: Operating System :: Microsoft :: Windows
Classifier: Programming Language :: Python
Classifier: Programming Language :: Python :: 3
Classifier: Programming Language :: Python :: 3 :: Only
Classifier: Programming Language :: Python :: 3.9
Classifier: Programming Language :: Python :: 3.10
Requires-Python: >=3.10
License-File: LICENSE
Requires-Dist: importlib-metadata (>=3.6)
